{
  "filename": "kilter_image16840.png",
  "rows": 34,
  "cols": 35,
  "channels": [
    "start",
    "finish",
    "hand",
    "foot",
    "hold_presence",
    "hold_size",
    "orient_sin1",
    "orient_cos1",
    "orient_sin2",
    "orient_cos2"
  ],
  "ring_counts": {
    "start": 1,
    "finish": 1,
    "hand": 6,
    "foot": 5
  },
  "raw_text": "eam racer low traine\nbigboiclimber\n\n7c/V9 Ye vee\n",
  "lines": [
    "eam racer low traine",
    "bigboiclimber",
    "7c/V9 Ye vee"
  ],
  "name": "eam racer low traine",
  "setter": "bigboiclimber",
  "grade_raw": "7c/V9 Ye vee",
  "grade_v": 9,
  "stars": 3
}