{
  "filename": "kilter_image23386.png",
  "rows": 34,
  "cols": 35,
  "channels": [
    "start",
    "finish",
    "hand",
    "foot",
    "hold_presence",
    "hold_size"
  ],
  "ring_counts": {
    "start": 2,
    "finish": 1,
    "hand": 6,
    "foot": 5
  },
  "raw_text": "Barrel Roll\ntrendyrendy\n\nZat/V7 Yeo.\n",
  "lines": [
    "Barrel Roll",
    "trendyrendy",
    "Zat/V7 Yeo."
  ],
  "name": "Barrel Roll",
  "setter": "trendyrendy",
  "grade_raw": "Zat/V7 Yeo.",
  "grade_v": 7,
  "stars": 3
}